<?xml version="1.0" encoding="UTF-8"?>
<!DOCTYPE mapper PUBLIC "-//mybatis.org//DTD Mapper 3.0//EN" "http://mybatis.org/dtd/mybatis-3-mapper.dtd">
<mapper namespace="survey">
  <resultMap id="BaseResultMap" type="com.survey.panelsns.model.entity.Survey">
    <!--
      WARNING - @mbggenerated
      This element is automatically generated by MyBatis Generator, do not modify.
      This element was generated on Sat Aug 25 14:14:03 CST 2012.
    -->
    <id column="id" jdbcType="BIGINT" property="id" />
    <result column="project_id" jdbcType="BIGINT" property="projectId" />
    <result column="industry" jdbcType="INTEGER" property="industry" />
    <result column="name" jdbcType="VARCHAR" property="name" />
    <result column="need_panel_num" jdbcType="INTEGER" property="needPanelNum" />
    <result column="endow_point" jdbcType="INTEGER" property="endowPoint" />
    <result column="hortation_point" jdbcType="INTEGER" property="hortationPoint" />
    <result column="begin_date" jdbcType="DATE" property="beginDate" />
    <result column="end_date" jdbcType="DATE" property="endDate" />
    <result column="cancle_date" jdbcType="DATE" property="cancleDate" />
    <result column="create_date" jdbcType="DATE" property="createDate" />
    <result column="descript" jdbcType="VARCHAR" property="descript" />
    <result column="status" jdbcType="INTEGER" property="status" />
    <result column="version" jdbcType="INTEGER" property="version" />
    <result column="remark" jdbcType="VARCHAR" property="remark" />
  </resultMap>
  <sql id="Example_Where_Clause">
    <!--
      WARNING - @mbggenerated
      This element is automatically generated by MyBatis Generator, do not modify.
      This element was generated on Sat Aug 25 14:14:03 CST 2012.
    -->
    <where>
      <foreach collection="oredCriteria" item="criteria" separator="or">
        <if test="criteria.valid">
          <trim prefix="(" prefixOverrides="and" suffix=")">
            <foreach collection="criteria.criteria" item="criterion">
              <choose>
                <when test="criterion.noValue">
                  and ${criterion.condition}
                </when>
                <when test="criterion.singleValue">
                  and ${criterion.condition} #{criterion.value}
                </when>
                <when test="criterion.betweenValue">
                  and ${criterion.condition} #{criterion.value} and #{criterion.secondValue}
                </when>
                <when test="criterion.listValue">
                  and ${criterion.condition}
                  <foreach close=")" collection="criterion.value" item="listItem" open="(" separator=",">
                    #{listItem}
                  </foreach>
                </when>
              </choose>
            </foreach>
          </trim>
        </if>
      </foreach>
    </where>
  </sql>
  <sql id="Update_By_Example_Where_Clause">
    <!--
      WARNING - @mbggenerated
      This element is automatically generated by MyBatis Generator, do not modify.
      This element was generated on Sat Aug 25 14:14:03 CST 2012.
    -->
    <where>
      <foreach collection="example.oredCriteria" item="criteria" separator="or">
        <if test="criteria.valid">
          <trim prefix="(" prefixOverrides="and" suffix=")">
            <foreach collection="criteria.criteria" item="criterion">
              <choose>
                <when test="criterion.noValue">
                  and ${criterion.condition}
                </when>
                <when test="criterion.singleValue">
                  and ${criterion.condition} #{criterion.value}
                </when>
                <when test="criterion.betweenValue">
                  and ${criterion.condition} #{criterion.value} and #{criterion.secondValue}
                </when>
                <when test="criterion.listValue">
                  and ${criterion.condition}
                  <foreach close=")" collection="criterion.value" item="listItem" open="(" separator=",">
                    #{listItem}
                  </foreach>
                </when>
              </choose>
            </foreach>
          </trim>
        </if>
      </foreach>
    </where>
  </sql>
  <sql id="Base_Column_List">
    <!--
      WARNING - @mbggenerated
      This element is automatically generated by MyBatis Generator, do not modify.
      This element was generated on Sat Aug 25 14:14:03 CST 2012.
    -->
    id, project_id, industry, name, need_panel_num, endow_point, hortation_point, begin_date, 
    end_date, cancle_date, create_date, descript, status, version, remark
  </sql>
  <select id="selectByExample" parameterType="com.survey.panelsns.model.entity.SurveyExample" resultMap="BaseResultMap">
    <!--
      WARNING - @mbggenerated
      This element is automatically generated by MyBatis Generator, do not modify.
      This element was generated on Sat Aug 25 14:14:03 CST 2012.
    -->
    select
    <if test="distinct">
      distinct
    </if>
    <include refid="Base_Column_List" />
    from survey
    <if test="_parameter != null">
      <include refid="Example_Where_Clause" />
    </if>
    <if test="orderByClause != null">
      order by ${orderByClause}
    </if>
  </select>
  <select id="selectByPrimaryKey" parameterType="java.lang.Long" resultMap="BaseResultMap">
    <!--
      WARNING - @mbggenerated
      This element is automatically generated by MyBatis Generator, do not modify.
      This element was generated on Sat Aug 25 14:14:03 CST 2012.
    -->
    select 
    <include refid="Base_Column_List" />
    from survey
    where id = #{id,jdbcType=BIGINT}
  </select>
  <delete id="deleteByPrimaryKey" parameterType="java.lang.Long">
    <!--
      WARNING - @mbggenerated
      This element is automatically generated by MyBatis Generator, do not modify.
      This element was generated on Sat Aug 25 14:14:03 CST 2012.
    -->
    delete from survey
    where id = #{id,jdbcType=BIGINT}
  </delete>
  <delete id="deleteByExample" parameterType="com.survey.panelsns.model.entity.SurveyExample">
    <!--
      WARNING - @mbggenerated
      This element is automatically generated by MyBatis Generator, do not modify.
      This element was generated on Sat Aug 25 14:14:03 CST 2012.
    -->
    delete from survey
    <if test="_parameter != null">
      <include refid="Example_Where_Clause" />
    </if>
  </delete>
  <insert id="insert" parameterType="com.survey.panelsns.model.entity.Survey">
    <!--
      WARNING - @mbggenerated
      This element is automatically generated by MyBatis Generator, do not modify.
      This element was generated on Sat Aug 25 14:14:03 CST 2012.
    -->
    insert into survey (id, project_id, industry, 
      name, need_panel_num, endow_point, 
      hortation_point, begin_date, end_date, 
      cancle_date, create_date, descript, 
      status, version, remark
      )
    values (#{id,jdbcType=BIGINT}, #{projectId,jdbcType=BIGINT}, #{industry,jdbcType=INTEGER}, 
      #{name,jdbcType=VARCHAR}, #{needPanelNum,jdbcType=INTEGER}, #{endowPoint,jdbcType=INTEGER}, 
      #{hortationPoint,jdbcType=INTEGER}, #{beginDate,jdbcType=DATE}, #{endDate,jdbcType=DATE}, 
      #{cancleDate,jdbcType=DATE}, #{createDate,jdbcType=DATE}, #{descript,jdbcType=VARCHAR}, 
      #{status,jdbcType=INTEGER}, #{version,jdbcType=INTEGER}, #{remark,jdbcType=VARCHAR}
      )
  </insert>
  <insert id="insertSelective" parameterType="com.survey.panelsns.model.entity.Survey">
    <!--
      WARNING - @mbggenerated
      This element is automatically generated by MyBatis Generator, do not modify.
      This element was generated on Sat Aug 25 14:14:03 CST 2012.
    -->
    insert into survey
    <trim prefix="(" suffix=")" suffixOverrides=",">
      <if test="id != null">
        id,
      </if>
      <if test="projectId != null">
        project_id,
      </if>
      <if test="industry != null">
        industry,
      </if>
      <if test="name != null">
        name,
      </if>
      <if test="needPanelNum != null">
        need_panel_num,
      </if>
      <if test="endowPoint != null">
        endow_point,
      </if>
      <if test="hortationPoint != null">
        hortation_point,
      </if>
      <if test="beginDate != null">
        begin_date,
      </if>
      <if test="endDate != null">
        end_date,
      </if>
      <if test="cancleDate != null">
        cancle_date,
      </if>
      <if test="createDate != null">
        create_date,
      </if>
      <if test="descript != null">
        descript,
      </if>
      <if test="status != null">
        status,
      </if>
      <if test="version != null">
        version,
      </if>
      <if test="remark != null">
        remark,
      </if>
    </trim>
    <trim prefix="values (" suffix=")" suffixOverrides=",">
      <if test="id != null">
        #{id,jdbcType=BIGINT},
      </if>
      <if test="projectId != null">
        #{projectId,jdbcType=BIGINT},
      </if>
      <if test="industry != null">
        #{industry,jdbcType=INTEGER},
      </if>
      <if test="name != null">
        #{name,jdbcType=VARCHAR},
      </if>
      <if test="needPanelNum != null">
        #{needPanelNum,jdbcType=INTEGER},
      </if>
      <if test="endowPoint != null">
        #{endowPoint,jdbcType=INTEGER},
      </if>
      <if test="hortationPoint != null">
        #{hortationPoint,jdbcType=INTEGER},
      </if>
      <if test="beginDate != null">
        #{beginDate,jdbcType=DATE},
      </if>
      <if test="endDate != null">
        #{endDate,jdbcType=DATE},
      </if>
      <if test="cancleDate != null">
        #{cancleDate,jdbcType=DATE},
      </if>
      <if test="createDate != null">
        #{createDate,jdbcType=DATE},
      </if>
      <if test="descript != null">
        #{descript,jdbcType=VARCHAR},
      </if>
      <if test="status != null">
        #{status,jdbcType=INTEGER},
      </if>
      <if test="version != null">
        #{version,jdbcType=INTEGER},
      </if>
      <if test="remark != null">
        #{remark,jdbcType=VARCHAR},
      </if>
    </trim>
  </insert>
  <select id="countByExample" parameterType="com.survey.panelsns.model.entity.SurveyExample" resultType="java.lang.Integer">
    <!--
      WARNING - @mbggenerated
      This element is automatically generated by MyBatis Generator, do not modify.
      This element was generated on Sat Aug 25 14:14:03 CST 2012.
    -->
    select count(*) from survey
    <if test="_parameter != null">
      <include refid="Example_Where_Clause" />
    </if>
  </select>
  <update id="updateByExampleSelective" parameterType="map">
    <!--
      WARNING - @mbggenerated
      This element is automatically generated by MyBatis Generator, do not modify.
      This element was generated on Sat Aug 25 14:14:03 CST 2012.
    -->
    update survey
    <set>
      <if test="record.id != null">
        id = #{record.id,jdbcType=BIGINT},
      </if>
      <if test="record.projectId != null">
        project_id = #{record.projectId,jdbcType=BIGINT},
      </if>
      <if test="record.industry != null">
        industry = #{record.industry,jdbcType=INTEGER},
      </if>
      <if test="record.name != null">
        name = #{record.name,jdbcType=VARCHAR},
      </if>
      <if test="record.needPanelNum != null">
        need_panel_num = #{record.needPanelNum,jdbcType=INTEGER},
      </if>
      <if test="record.endowPoint != null">
        endow_point = #{record.endowPoint,jdbcType=INTEGER},
      </if>
      <if test="record.hortationPoint != null">
        hortation_point = #{record.hortationPoint,jdbcType=INTEGER},
      </if>
      <if test="record.beginDate != null">
        begin_date = #{record.beginDate,jdbcType=DATE},
      </if>
      <if test="record.endDate != null">
        end_date = #{record.endDate,jdbcType=DATE},
      </if>
      <if test="record.cancleDate != null">
        cancle_date = #{record.cancleDate,jdbcType=DATE},
      </if>
      <if test="record.createDate != null">
        create_date = #{record.createDate,jdbcType=DATE},
      </if>
      <if test="record.descript != null">
        descript = #{record.descript,jdbcType=VARCHAR},
      </if>
      <if test="record.status != null">
        status = #{record.status,jdbcType=INTEGER},
      </if>
      <if test="record.version != null">
        version = #{record.version,jdbcType=INTEGER},
      </if>
      <if test="record.remark != null">
        remark = #{record.remark,jdbcType=VARCHAR},
      </if>
    </set>
    <if test="_parameter != null">
      <include refid="Update_By_Example_Where_Clause" />
    </if>
  </update>
  <update id="updateByExample" parameterType="map">
    <!--
      WARNING - @mbggenerated
      This element is automatically generated by MyBatis Generator, do not modify.
      This element was generated on Sat Aug 25 14:14:03 CST 2012.
    -->
    update survey
    set id = #{record.id,jdbcType=BIGINT},
      project_id = #{record.projectId,jdbcType=BIGINT},
      industry = #{record.industry,jdbcType=INTEGER},
      name = #{record.name,jdbcType=VARCHAR},
      need_panel_num = #{record.needPanelNum,jdbcType=INTEGER},
      endow_point = #{record.endowPoint,jdbcType=INTEGER},
      hortation_point = #{record.hortationPoint,jdbcType=INTEGER},
      begin_date = #{record.beginDate,jdbcType=DATE},
      end_date = #{record.endDate,jdbcType=DATE},
      cancle_date = #{record.cancleDate,jdbcType=DATE},
      create_date = #{record.createDate,jdbcType=DATE},
      descript = #{record.descript,jdbcType=VARCHAR},
      status = #{record.status,jdbcType=INTEGER},
      version = #{record.version,jdbcType=INTEGER},
      remark = #{record.remark,jdbcType=VARCHAR}
    <if test="_parameter != null">
      <include refid="Update_By_Example_Where_Clause" />
    </if>
  </update>
  <update id="updateByPrimaryKeySelective" parameterType="com.survey.panelsns.model.entity.Survey">
    <!--
      WARNING - @mbggenerated
      This element is automatically generated by MyBatis Generator, do not modify.
      This element was generated on Sat Aug 25 14:14:03 CST 2012.
    -->
    update survey
    <set>
      <if test="projectId != null">
        project_id = #{projectId,jdbcType=BIGINT},
      </if>
      <if test="industry != null">
        industry = #{industry,jdbcType=INTEGER},
      </if>
      <if test="name != null">
        name = #{name,jdbcType=VARCHAR},
      </if>
      <if test="needPanelNum != null">
        need_panel_num = #{needPanelNum,jdbcType=INTEGER},
      </if>
      <if test="endowPoint != null">
        endow_point = #{endowPoint,jdbcType=INTEGER},
      </if>
      <if test="hortationPoint != null">
        hortation_point = #{hortationPoint,jdbcType=INTEGER},
      </if>
      <if test="beginDate != null">
        begin_date = #{beginDate,jdbcType=DATE},
      </if>
      <if test="endDate != null">
        end_date = #{endDate,jdbcType=DATE},
      </if>
      <if test="cancleDate != null">
        cancle_date = #{cancleDate,jdbcType=DATE},
      </if>
      <if test="createDate != null">
        create_date = #{createDate,jdbcType=DATE},
      </if>
      <if test="descript != null">
        descript = #{descript,jdbcType=VARCHAR},
      </if>
      <if test="status != null">
        status = #{status,jdbcType=INTEGER},
      </if>
      <if test="version != null">
        version = #{version,jdbcType=INTEGER},
      </if>
      <if test="remark != null">
        remark = #{remark,jdbcType=VARCHAR},
      </if>
    </set>
    where id = #{id,jdbcType=BIGINT}
  </update>
  <update id="updateByPrimaryKey" parameterType="com.survey.panelsns.model.entity.Survey">
    <!--
      WARNING - @mbggenerated
      This element is automatically generated by MyBatis Generator, do not modify.
      This element was generated on Sat Aug 25 14:14:03 CST 2012.
    -->
    update survey
    set project_id = #{projectId,jdbcType=BIGINT},
      industry = #{industry,jdbcType=INTEGER},
      name = #{name,jdbcType=VARCHAR},
      need_panel_num = #{needPanelNum,jdbcType=INTEGER},
      endow_point = #{endowPoint,jdbcType=INTEGER},
      hortation_point = #{hortationPoint,jdbcType=INTEGER},
      begin_date = #{beginDate,jdbcType=DATE},
      end_date = #{endDate,jdbcType=DATE},
      cancle_date = #{cancleDate,jdbcType=DATE},
      create_date = #{createDate,jdbcType=DATE},
      descript = #{descript,jdbcType=VARCHAR},
      status = #{status,jdbcType=INTEGER},
      version = #{version,jdbcType=INTEGER},
      remark = #{remark,jdbcType=VARCHAR}
    where id = #{id,jdbcType=BIGINT}
  </update>
</mapper>